README.md
setup.py
image_renamer/__init__.py
image_renamer/__main__.py
image_renamer/image_renamer.py
image_renamer.egg-info/PKG-INFO
image_renamer.egg-info/SOURCES.txt
image_renamer.egg-info/dependency_links.txt
image_renamer.egg-info/entry_points.txt
image_renamer.egg-info/requires.txt
image_renamer.egg-info/top_level.txt