Metadata-Version: 2.1
Name: image-renamer
Version: 0.1.3
Summary: Simple bulk image timestamps renamer
Home-page: https://github.com/JozefGalbicka/image-renamer.git
Author: Jozef Galbicka
Author-email: alerts.cryp@gmail.com
License: MIT
Platform: UNKNOWN
Classifier: Development Status :: 3 - Alpha
Classifier: License :: OSI Approved :: MIT License
Classifier: Programming Language :: Python
Classifier: Programming Language :: Python :: 3
Classifier: Programming Language :: Python :: 3.9
Classifier: Topic :: Utilities
Classifier: Topic :: Multimedia
Classifier: Topic :: System :: Filesystems
